quizapp/__init__.py
quizapp/main.py
quizapp/assets/quizzes/DATA-533.json
quizapp/assets/scores/DATA-533_scores.csv
quizapp/student/__init__.py
quizapp/student/readquiz.py
quizapp/student/takequiz.py
quizapp/teacher/__init__.py
quizapp/teacher/checkstudentscores.py
quizapp/teacher/createquiz.py
quizapp-1.0.3.dist-info/LICENCE.txt
quizapp-1.0.3.dist-info/METADATA
quizapp-1.0.3.dist-info/WHEEL
quizapp-1.0.3.dist-info/top_level.txt
quizapp-1.0.3.dist-info/RECORD
