Metadata-Version: 2.1
Name: quizapp
Version: 1.0.3
Summary: A quiz app
Author-email: Dylan Longert <longert520@gmail.com>, Somya Nagar <somyanagar49@gmail.com>
Project-URL: Homepage, https://github.com/somyanagar/quizapp_CI.git
Classifier: Programming Language :: Python :: 3
Classifier: License :: OSI Approved :: MIT License
Classifier: Operating System :: OS Independent
Requires-Python: >=3.8
License-File: LICENCE.txt
